xarray_quantity/__init__.py
xarray_quantity/quantity_array.py
xarray_quantity/quantity_set.py
xarray_quantity-0.1.5.dist-info/LICENSE
xarray_quantity-0.1.5.dist-info/WHEEL
xarray_quantity-0.1.5.dist-info/METADATA
xarray_quantity-0.1.5.dist-info/RECORD
