Metadata-Version: 2.1
Name: xarray-quantity
Version: 0.1.5
Summary: xarray extension which supports astropy quantities.
Home-page: https://github.com/KaoruNishikawa/xarray-quantity
License: MIT
Author: KaoruNishikawa
Author-email: k.nishikawa@a.phys.nagoya-u.ac.jp
Requires-Python: >=3.8,<4.0
Classifier: License :: OSI Approved :: MIT License
Classifier: Programming Language :: Python :: 3
Classifier: Programming Language :: Python :: 3.10
Classifier: Programming Language :: Python :: 3.8
Classifier: Programming Language :: Python :: 3.9
Requires-Dist: astropy (>5.0.3)
Requires-Dist: xarray (>2022)
Project-URL: Repository, https://github.com/KaoruNishikawa/xarray-quantity
